nbforms/__init__.py
nbforms/version.py
nbforms/widgets.py
test/__init__.py
test/test_form.py
nbforms-1.0.0.dist-info/LICENSE
nbforms-1.0.0.dist-info/METADATA
nbforms-1.0.0.dist-info/WHEEL
nbforms-1.0.0.dist-info/top_level.txt
nbforms-1.0.0.dist-info/RECORD
