Metadata-Version: 2.1
Name: nbforms
Version: 1.0.0
Summary: Jupyter Notebook forms using ipywidgets
Home-page: https://github.com/chrispyles/nbforms
Author: Chris Pyles
Author-email: cpyles@berkeley.edu
License: BSD-3-Clause
Classifier: Programming Language :: Python :: 3
Classifier: License :: OSI Approved :: BSD License
Classifier: Operating System :: OS Independent
License-File: LICENSE
